{
  "name": "Deploy-SLZ-Decom-Deployment",
  "type": "Microsoft.Authorization/policyAssignments",
  "apiVersion": "2019-09-01",
  "properties": {
    "description": "SLZ Decommissioned Policies",
    "displayName": "SLZ Decommissioned Policies",
    "notScopes": [],
    "parameters": {},
    "policyDefinitionId": "${varTargetManagementGroupResourceId}/providers/Microsoft.Authorization/policySetDefinitions/SlzDecommissionedPolicies",
    "scope": null,
    "enforcementMode": "Default"
  },
  "location": null,
  "identity": {
    "type": "SystemAssigned"
  }
}
